README.rst
setup.py
mtgjson/__init__.py
mtgjson/jsonproxy.py
mtgjson.egg-info/PKG-INFO
mtgjson.egg-info/SOURCES.txt
mtgjson.egg-info/dependency_links.txt
mtgjson.egg-info/requires.txt
mtgjson.egg-info/top_level.txt