Metadata-Version: 1.0
Name: mtgjson
Version: 0.3
Summary: A python library for working with data from mtgjson.com.
Home-page: http://github.com/mbr/pymtgjson
Author: Marc Brinkmann
Author-email: git@marcbrinkmann.de
License: MIT
Platform: UNKNOWN
